setup.py
brew/__init__.py
brew/cron.py
brew_cron.egg-info/PKG-INFO
brew_cron.egg-info/SOURCES.txt
brew_cron.egg-info/dependency_links.txt
brew_cron.egg-info/entry_points.txt
brew_cron.egg-info/top_level.txt