Metadata-Version: 1.0
Name: brew-cron
Version: 0.1
Summary: A helper for Homebrew operations from cron
Home-page: UNKNOWN
Author: Kunal Mehta
Author-email: legoktm@gmail.com
License: CC-0
Platform: UNKNOWN
